aidriven_my_project/__init__.py
aidriven_my_project-0.1.0.dist-info/METADATA
aidriven_my_project-0.1.0.dist-info/WHEEL
aidriven_my_project-0.1.0.dist-info/RECORD
