Metadata-Version: 2.1
Name: aidriven-my-project
Version: 0.1.0
Summary: 
Author: Takuya Sato
Author-email: business@satotakuya.jp
Requires-Python: >=3.12,<4.0
Classifier: Programming Language :: Python :: 3
Classifier: Programming Language :: Python :: 3.12
Classifier: Programming Language :: Python :: 3.13
Requires-Dist: requests (>=2.32.3,<3.0.0)
